arthur_observability_sdk/__init__.py
arthur_observability_sdk/_generated/.gitignore
arthur_observability_sdk/_generated/README.md
arthur_observability_sdk/_generated/__init__.py
arthur_observability_sdk/_generated/api/__init__.py
arthur_observability_sdk/_generated/api/api_keys/__init__.py
arthur_observability_sdk/_generated/api/api_keys/create_api_key_auth_api_keys_post.py
arthur_observability_sdk/_generated/api/api_keys/deactivate_api_key_auth_api_keys_deactivate_api_key_id_delete.py
arthur_observability_sdk/_generated/api/api_keys/get_all_active_api_keys_auth_api_keys_get.py
arthur_observability_sdk/_generated/api/api_keys/get_api_key_auth_api_keys_api_key_id_get.py
arthur_observability_sdk/_generated/api/chat/__init__.py
arthur_observability_sdk/_generated/api/chat/chat_request.py
arthur_observability_sdk/_generated/api/chat/delete_file_api_chat_files_file_id_delete.py
arthur_observability_sdk/_generated/api/chat/get_conversations_api_chat_conversations_get.py
arthur_observability_sdk/_generated/api/chat/get_default_task_api_chat_default_task_get.py
arthur_observability_sdk/_generated/api/chat/get_files_api_chat_files_get.py
arthur_observability_sdk/_generated/api/chat/get_inference_document_context_api_chat_context_inference_id_get.py
arthur_observability_sdk/_generated/api/chat/post_chat_feedback_api_chat_feedback_inference_id_post.py
arthur_observability_sdk/_generated/api/chat/update_default_task_api_chat_default_task_put.py
arthur_observability_sdk/_generated/api/chat/upload_embeddings_file_api_chat_files_post.py
arthur_observability_sdk/_generated/api/continuous_evals/__init__.py
arthur_observability_sdk/_generated/api/continuous_evals/create_continuous_eval_api_v1_tasks_task_id_continuous_evals_post.py
arthur_observability_sdk/_generated/api/continuous_evals/delete_continuous_eval_api_v1_continuous_evals_eval_id_delete.py
arthur_observability_sdk/_generated/api/continuous_evals/get_continuous_eval_by_id_api_v1_continuous_evals_eval_id_get.py
arthur_observability_sdk-0.1.0.dist-info/METADATA
arthur_observability_sdk-0.1.0.dist-info/WHEEL
arthur_observability_sdk-0.1.0.dist-info/RECORD
