Metadata-Version: 2.3
Name: arthur-observability-sdk
Version: 0.1.0
Summary: Official Python SDK for Arthur platform APIs and OpenInference tracing
License: Apache-2.0
Keywords: arthur,observability,tracing,opentelemetry,openinference,llm,monitoring
Author: Arthur
Author-email: engineering@arthur.ai
Requires-Python: >=3.8
Classifier: Development Status :: 4 - Beta
Classifier: Intended Audience :: Developers
Classifier: License :: OSI Approved :: Apache Software License
Classifier: Programming Language :: Python :: 3
Classifier: Programming Language :: Python :: 3.8
Classifier: Programming Language :: Python :: 3.9
Classifier: Programming Language :: Python :: 3.10
Classifier: Programming Language :: Python :: 3.11
Classifier: Programming Language :: Python :: 3.12
Classifier: Topic :: Software Development :: Libraries :: Python Modules
Classifier: Topic :: System :: Monitoring
Provides-Extra: all
Provides-Extra: anthropic
Provides-Extra: bedrock
Provides-Extra: dev
Provides-Extra: groq
Provides-Extra: langchain
Provides-Extra: llama-index
Provides-Extra: mistralai
Provides-Extra: openai
Provides-Extra: vertexai
Requires-Dist: black (>=23.0.0) ; extra == "dev"
Requires-Dist: mypy (>=1.0.0) ; extra == "dev"
Requires-Dist: openapi-python-client (>=0.21.0) ; extra == "dev"
Requires-Dist: openinference-instrumentation (>=0.1.0)
Requires-Dist: openinference-instrumentation-anthropic (>=0.1.0) ; extra == "all"
Requires-Dist: openinference-instrumentation-anthropic (>=0.1.0) ; extra == "anthropic"
Requires-Dist: openinference-instrumentation-bedrock (>=0.1.0) ; extra == "all"
Requires-Dist: openinference-instrumentation-bedrock (>=0.1.0) ; extra == "bedrock"
Requires-Dist: openinference-instrumentation-groq (>=0.1.0) ; extra == "all"
Requires-Dist: openinference-instrumentation-groq (>=0.1.0) ; extra == "groq"
Requires-Dist: openinference-instrumentation-langchain (>=0.1.0) ; extra == "all"
Requires-Dist: openinference-instrumentation-langchain (>=0.1.0) ; extra == "langchain"
Requires-Dist: openinference-instrumentation-llama-index (>=0.1.0) ; extra == "all"
Requires-Dist: openinference-instrumentation-llama-index (>=0.1.0) ; extra == "llama-index"
Requires-Dist: openinference-instrumentation-mistralai (>=0.1.0) ; extra == "all"
Requires-Dist: openinference-instrumentation-mistralai (>=0.1.0) ; extra == "mistralai"
Requires-Dist: openinference-instrumentation-openai (>=0.1.0) ; extra == "all"
Requires-Dist: openinference-instrumentation-openai (>=0.1.0) ; extra == "openai"
Requires-Dist: openinference-instrumentation-vertexai (>=0.1.0) ; extra == "all"
Requires-Dist: openinference-instrumentation-vertexai (>=0.1.0) ; extra == "vertexai"
Requires-Dist: opentelemetry-api (>=1.20.0)
Requires-Dist: opentelemetry-exporter-otlp-proto-http (>=1.20.0)
Requires-Dist: opentelemetry-sdk (>=1.20.0)
Requires-Dist: pytest (>=7.0.0) ; extra == "dev"
Requires-Dist: pytest-mock (>=3.10.0) ; extra == "dev"
Requires-Dist: ruff (>=0.1.0) ; extra == "dev"
Project-URL: Bug Tracker, https://github.com/arthur-ai/arthur-engine/issues
Project-URL: Documentation, https://docs.arthur.ai
Project-URL: Discord, https://discord.gg/tdfUAtaVHz
Project-URL: Homepage, https://arthur.ai
Project-URL: Repository, https://github.com/arthur-ai/arthur-engine
